gmails/__init__.py
gmails/retriever.py
gmails-0.3.1.dist-info/LICENSE
gmails-0.3.1.dist-info/METADATA
gmails-0.3.1.dist-info/WHEEL
gmails-0.3.1.dist-info/top_level.txt
gmails-0.3.1.dist-info/RECORD
